pyjath
