Metadata-Version: 1.0
Name: pyjath
Version: 0.0.5
Summary: Template based xml to python data structure conversion.
Home-page: http://packages.python.org/pyjath
Author: Dan Newcome
Author-email: dan@dnuke.com
License: BSD
Keywords: xml
Platform: UNKNOWN
Classifier: Development Status :: 3 - Alpha
Classifier: Topic :: Software Development :: Libraries
Classifier: License :: OSI Approved :: BSD License
